midlife.py
midlife-0.0.8.dist-info/METADATA
midlife-0.0.8.dist-info/WHEEL
midlife-0.0.8.dist-info/entry_points.txt
midlife-0.0.8.dist-info/top_level.txt
midlife-0.0.8.dist-info/RECORD
