Metadata-Version: 2.1
Name: midlife
Version: 0.0.8
Summary: impact of COVID-19 on mortality of midlife
Home-page: https://github.com/y-takefuji/midlife
Author: yoshiyasu takefuji
Author-email: takefuji@keio.jp
Project-URL: Bug Tracker, https://github.com/y-takefuji/midlife
Classifier: Programming Language :: Python :: 3
Classifier: License :: OSI Approved :: MIT License
Classifier: Operating System :: OS Independent
Requires-Python: >=3.8
